DBSegment/DBSegment.py
DBSegment/__init__.py
DBSegment-0.2.2.dist-info/LICENSE
DBSegment-0.2.2.dist-info/METADATA
DBSegment-0.2.2.dist-info/WHEEL
DBSegment-0.2.2.dist-info/entry_points.txt
DBSegment-0.2.2.dist-info/top_level.txt
DBSegment-0.2.2.dist-info/RECORD
