Metadata-Version: 2.1
Name: DBSegment
Version: 0.2.2
Summary: A deep learning based method to segment deep brain structures from T1w MRI
Author: Mehri
Author-email: mehri.baniasadi92@gmail.com
Keywords: python
Classifier: Development Status :: 1 - Planning
Classifier: Intended Audience :: Developers
Classifier: Programming Language :: Python :: 3
Classifier: Operating System :: Unix
Classifier: Operating System :: MacOS :: MacOS X
Classifier: Operating System :: Microsoft :: Windows
License-File: LICENSE
Requires-Dist: nibabel ==5.2.1
Requires-Dist: scipy ==1.13.1
Requires-Dist: torch ==2.3.0
Requires-Dist: requests ==2.32.2
Requires-Dist: antspyx ==0.4.2
Requires-Dist: nnunet ==1.7.1
